{"id":"7sv6nsm7mek2rulnozsg5ba","title":"Scope","desc":"","updated":1671214093931,"created":1671213692111,"custom":{},"fname":"javascript.variables.scope","type":"note","vault":{"fsPath":".","selfContained":true,"name":"JS109_assessment"},"contentHash":"3d403a008856f384013443cc51e17b36","links":[],"anchors":{"variable-scope-in-javascript":{"type":"header","text":"Variable scope in JavaScript","value":"variable-scope-in-javascript","line":7,"column":0,"depth":2}},"children":[],"parent":"0m6wvk9qd52ss46rxaeguta","data":{}}
